we_love/cli/__init__.py
we_love/cli/pydantic_app.py
we_love_cli-0.1.0.dist-info/WHEEL
we_love_cli-0.1.0.dist-info/METADATA
we_love_cli-0.1.0.dist-info/RECORD
