Metadata-Version: 2.3
Name: we-love-cli
Version: 0.1.0
Summary: CLI utilities for the we-love namespace
Classifier: Programming Language :: Python :: 3 :: Only
Classifier: Programming Language :: Python :: 3.13
Requires-Python: >=3.13
